{
	"failures":
	{
	    "0x2000" : "Изменение статуса m_energysafe, Режим энергосбережения OFF",
		"0x2001" : "Изменение статуса m_energysafe, Режим энергосбережения ON",
		"0x2010" : "Изменение статуса m_arm, Режим «охрана» OFF",
		"0x2011" : "Изменение статуса m_arm, Режим «охрана» ON",
		"0x2020" : "Изменение статуса m_disarm, Режим «снято с охраны» OFF",
		"0x2021" : "Изменение статуса m_disarm, Режим «снято с охраны» ON",
		"0x2030" : "Изменение статуса m_overwrite_pin, Режим «перезаписи PIN-кода» OFF",
		"0x2031" : "Изменение статуса m_overwrite_pin, Режим «перезаписи PIN-кода» ON",
		"0x2040" : "Изменение статуса m_change_pin, Режим «смены PIN-кода» OFF",
		"0x2041" : "Изменение статуса m_change_pin, Режим «смены PIN-кода» ON",
		"0x2050" : "Изменение статуса m_wait_change_pin, Режим «записи нового/смены PIN-кода» OFF",
		"0x2051" : "Изменение статуса m_wait_change_pin, Режим «записи нового/смены PIN-кода» ON",
		"0x2060" : "Изменение статуса m_wait_reapit_pin, Режим «ожидания повтора ввода нового PIN-кода» OFF",
		"0x2061" : "Изменение статуса m_wait_reapit_pin, Режим «ожидания повтора ввода нового PIN-кода» ON",
		"0x2070" : "Изменение статуса m_reapit_pin, Режим «повтора ввода нового PIN-кода» OFF",
		"0x2071" : "Изменение статуса m_reapit_pin, Режим «повтора ввода нового PIN-кода» ON",
		"0x2080" : "Изменение статуса m_wait_authorisation, Режим «ожидания авторизации» OFF",
		"0x2081" : "Изменение статуса m_wait_authorisation, Режим «ожидания авторизации» ON",
		"0x2090" : "Изменение статуса m_block_engine, Режим «блокировки работающего двигателя» OFF",
		"0x2091" : "Изменение статуса m_block_engine, Режим «блокировки работающего двигателя» ON",
		"0x20A0" : "Изменение статуса m_block_start, Режим «блокировки запуска двигателя» OFF",
		"0x20A1" : "Изменение статуса m_block_start, Режим «блокировки запуска двигателя» ON",
		"0x20B0" : "Изменение статуса m_service, Режим «Сервисный режим» OFF",
		"0x20B1" : "Изменение статуса m_service, Режим «Сервисный режим» ON",
		"0x20C0" : "Изменение статуса m_ahj, Режим «анти ограбление» OFF",
		"0x20C1" : "Изменение статуса m_ahj, Режим «анти ограбление» ON",
		"0x20D0" : "Изменение статуса m_analog_block, Режим «Аналоговая блокировка» OFF",
		"0x20D1" : "Изменение статуса m_analog_block, Режим «Аналоговая блокировка» ON",
		"0x3001" : "Неверный статус ign_s. От скорости",
		"0x3002" : "Неверный статус engine_s. От скорости",
		"0x3003" : "Неверный статус ign_s. От двигателя",
		"0x3004" : "Неверный статус starter_s. От скорости",
		"0x3005" : "Неверный статус starter_s. От АКПП",
		"0x3006" : "Неверный статус trans_p_s. От скорости ",
		"0x3007" : "Неверный статус rpm_s. От скорости",
		"0x3008" : "Неверный статус speed_over_50_s. От двери",
		"0x3009" : "Неверный статус rpm_s. От двигателя",
		"0x300D" : "Неверный статус engine_S. От оборотов",
		"0x300A" : "Неверное подключение питания устройства. От скорости",
		"0x300B" : "Неверное подключение питания устройства. От двигателя",
		"0x300C" : "Неверное подключение питания устройства. От стартера",
		"0x3100" : "can_change Зажигание ВЫКЛ",
		"0x3101" : "can_change Зажигание ВКЛ",
		"0x3110" : "can_change Стартер ВЫКЛ",
		"0x3111" : "can_change Стартер ВКЛ",
		"0x3120" : "can_change Двигатель ВЫКЛ",
		"0x3121" : "can_change Двигатель ВКЛ",
		"0x3130" : "can_change Педаль газа ВЫКЛ",
		"0x3131" : "can_change Педаль газа ВКЛ",
		"0x3140" : "can_change Педаль газа > 90% ВЫКЛ",
		"0x3141" : "can_change Педаль газа > 90% ВКЛ",
		"0x3150" : "can_change АКПП Parking ВЫКЛ",
		"0x3151" : "can_change АКПП Parking ВКЛ",
		"0x3160" : "can_change Скорость от 0 до 5 км/ч ВЫКЛ",
		"0x3161" : "can_change Скорость от 0 до 5 км/ч ВКЛ",
		"0x3170" : "can_change Скорость выше 5 км/ч ВЫКЛ",
		"0x3171" : "can_change Скорость выше 5 км/ч ВКЛ",
		"0x3180" : "can_change Скорость выше 50 км/ч ВЫКЛ",
		"0x3181" : "can_change Скорость выше 50 км/ч ВКЛ",
		"0x3190" : "can_change Педаль сцепления ВЫКЛ",
		"0x3191" : "can_change Педаль сцепления ВКЛ",
		"0x31A0" : "can_change Дверь открыта ВЫКЛ",
		"0x31A1" : "can_change Дверь открыта ВКЛ",
		"0x31B0" : "can_change Нажатие на тормоз ВЫКЛ",
		"0x31B1" : "can_change Нажатие на тормоз ВКЛ",
		"0x31C0" : "can_change АКПП Neutral ВЫКЛ",
		"0x31C1" : "can_change АКПП Neutral ВКЛ",
		"0x31D0" : "can_change Engine RPM > 0 ВЫКЛ",
		"0x31D1" : "can_change Engine RPM > 0 ВКЛ",
		"0x3200" : "can_change BUTTON 1 Отпущена",
		"0x3201" : "can_change BUTTON 1 Нажата",
		"0x3210" : "can_change BUTTON 2 Отпущена",
		"0x3211" : "can_change BUTTON 2 Нажата",
		"0x3220" : "can_change BUTTON 3 Отпущена",
		"0x3221" : "can_change BUTTON 3 Нажата",
		"0x3230" : "can_change BUTTON 4 Отпущена",
		"0x3231" : "can_change BUTTON 4 Нажата",
		"0x3240" : "can_change BUTTON 5 Отпущена",
		"0x3241" : "can_change BUTTON 5 Нажата",
		"0x3250" : "can_change BUTTON 6 Отпущена",
		"0x3251" : "can_change BUTTON 6 Нажата"
	}
}